{"data":[{"timestamp":"2024-12-06T01:37:04.345Z","domain":"pubsub.googleapis.com","root":"pubsub.googleapis.com","tracker":"googleapis.com","type":"A","dnssec":false,"encrypted":false,"protocol":"UDP","clientIp":"2804:678c:c176:d500:bb43:b9d2:5d09:4def","status":"default","reasons":[]},{"timestamp":"2024-12-06T01:37:04.340Z","domain":"pubsub.googleapis.com","root":"pubsub.googleapis.com","tracker":"googleapis.com","type":"AAAA","dnssec":false,"encrypted":false,"protocol":"UDP","clientIp":"2804:678c:c176:d500:bb43:b9d2:5d09:4def","status":"default","reasons":[]},{"timestamp":"2024-12-06T01:37:02.764Z","domain":"b1.nel.goog","root":"nel.goog","type":"AAAA","dnssec":false,"encrypted":false,"protocol":"UDP","clientIp":"45.190.211.163","status":"default","reasons":[]},{"timestamp":"2024-12-06T01:37:02.763Z","domain":"b1.nel.goog","root":"nel.goog","type":"HTTPS","dnssec":false,"encrypted":false,"protocol":"UDP","clientIp":"45.190.211.163","status":"default","reasons":[]},{"timestamp":"2024-12-06T01:37:02.763Z","domain":"b1.nel.goog","root":"nel.goog","type":"A","dnssec":false,"encrypted":false,"protocol":"UDP","clientIp":"45.190.211.163","status":"default","reasons":[]},{"timestamp":"2024-12-06T01:37:00.735Z","domain":"api-28-0-0.twitter.com","root":"twitter.com","tracker":"twitter","type":"AAAA","dnssec":false,"encrypted":false,"protocol":"UDP","clientIp":"2804:678c:c176:d500:d47:6f35:ada:bde0","status":"default","reasons":[]},{"timestamp":"2024-12-06T01:36:57.566Z","domain":"msd1-api.twitter.com","root":"twitter.com","tracker":"twitter","type":"A","dnssec":false,"encrypted":false,"protocol":"UDP","clientIp":"2804:678c:c176:d500:d47:6f35:ada:bde0","status":"default","reasons":[]},{"timestamp":"2024-12-06T01:36:57.565Z","domain":"msd1-api.twitter.com","root":"twitter.com","tracker":"twitter","type":"AAAA","dnssec":false,"encrypted":false,"protocol":"UDP","clientIp":"2804:678c:c176:d500:d47:6f35:ada:bde0","status":"default","reasons":[]},{"timestamp":"2024-12-06T01:36:49.652Z","domain":"abs-0.twimg.com","root":"twimg.com","tracker":"twitter","type":"AAAA","dnssec":false,"encrypted":false,"protocol":"UDP","clientIp":"2804:678c:c176:d500:bb43:b9d2:5d09:4def","status":"default","reasons":[]},{"timestamp":"2024-12-06T01:36:49.652Z","domain":"abs-0.twimg.com","root":"twimg.com","tracker":"twitter","type":"A","dnssec":false,"encrypted":false,"protocol":"UDP","clientIp":"2804:678c:c176:d500:bb43:b9d2:5d09:4def","status":"default","reasons":[]},{"timestamp":"2024-12-06T01:36:26.533Z","domain":"content-autofill.googleapis.com","root":"content-autofill.googleapis.com","tracker":"googleapis.com","type":"A","dnssec":false,"encrypted":false,"protocol":"UDP","clientIp":"2804:678c:c176:d500:bb43:b9d2:5d09:4def","status":"default","reasons":[]},{"timestamp":"2024-12-06T01:36:26.531Z","domain":"content-autofill.googleapis.com","root":"content-autofill.googleapis.com","tracker":"googleapis.com","type":"AAAA","dnssec":false,"encrypted":false,"protocol":"UDP","clientIp":"2804:678c:c176:d500:bb43:b9d2:5d09:4def","status":"default","reasons":[]},{"timestamp":"2024-12-06T01:36:25.853Z","domain":"rr3---sn-ov8xaauxaxjvhcg-jbie.googlevideo.com","root":"googlevideo.com","tracker":"youtube","type":"A","dnssec":false,"encrypted":false,"protocol":"UDP","clientIp":"2804:678c:c176:d500:bb43:b9d2:5d09:4def","status":"default","reasons":[]},{"timestamp":"2024-12-06T01:36:25.849Z","domain":"rr3---sn-ov8xaauxaxjvhcg-jbie.googlevideo.com","root":"googlevideo.com","tracker":"youtube","type":"AAAA","dnssec":false,"encrypted":false,"protocol":"UDP","clientIp":"2804:678c:c176:d500:bb43:b9d2:5d09:4def","status":"default","reasons":[]},{"timestamp":"2024-12-06T01:36:25.830Z","domain":"rr3---sn-ov8xaauxaxjvhcg-jbil.googlevideo.com","root":"googlevideo.com","tracker":"youtube","type":"A","dnssec":false,"encrypted":false,"protocol":"UDP","clientIp":"2804:678c:c176:d500:bb43:b9d2:5d09:4def","status":"default","reasons":[]},{"timestamp":"2024-12-06T01:36:25.827Z","domain":"rr3---sn-ov8xaauxaxjvhcg-jbil.googlevideo.com","root":"googlevideo.com","tracker":"youtube","type":"A","dnssec":false,"encrypted":false,"protocol":"UDP","clientIp":"2804:678c:c176:d500:bb43:b9d2:5d09:4def","status":"default","reasons":[]},{"timestamp":"2024-12-06T01:36:25.827Z","domain":"rr3---sn-ov8xaauxaxjvhcg-jbil.googlevideo.com","root":"googlevideo.com","tracker":"youtube","type":"AAAA","dnssec":false,"encrypted":false,"protocol":"UDP","clientIp":"2804:678c:c176:d500:bb43:b9d2:5d09:4def","status":"default","reasons":[]},{"timestamp":"2024-12-06T01:36:25.826Z","domain":"rr3---sn-ov8xaauxaxjvhcg-jbil.googlevideo.com","root":"googlevideo.com","tracker":"youtube","type":"AAAA","dnssec":false,"encrypted":false,"protocol":"UDP","clientIp":"2804:678c:c176:d500:bb43:b9d2:5d09:4def","status":"default","reasons":[]},{"timestamp":"2024-12-06T01:36:25.704Z","domain":"rr2---sn-ov8xaauxaxjvhcg-jbil.googlevideo.com","root":"googlevideo.com","tracker":"youtube","type":"A","dnssec":false,"encrypted":false,"protocol":"UDP","clientIp":"2804:678c:c176:d500:bb43:b9d2:5d09:4def","status":"default","reasons":[]},{"timestamp":"2024-12-06T01:36:25.703Z","domain":"rr2---sn-ov8xaauxaxjvhcg-jbil.googlevideo.com","root":"googlevideo.com","tracker":"youtube","type":"AAAA","dnssec":false,"encrypted":false,"protocol":"UDP","clientIp":"2804:678c:c176:d500:bb43:b9d2:5d09:4def","status":"default","reasons":[]},{"timestamp":"2024-12-06T01:36:25.457Z","domain":"cm.g.doubleclick.net","root":"doubleclick.net","tracker":"doubleclick","type":"A","dnssec":false,"encrypted":false,"protocol":"UDP","clientIp":"2804:678c:c176:d500:bb43:b9d2:5d09:4def","status":"default","reasons":[]},{"timestamp":"2024-12-06T01:36:25.451Z","domain":"cm.g.doubleclick.net","root":"doubleclick.net","tracker":"doubleclick","type":"AAAA","dnssec":false,"encrypted":false,"protocol":"UDP","clientIp":"2804:678c:c176:d500:bb43:b9d2:5d09:4def","status":"default","reasons":[]},{"timestamp":"2024-12-06T01:36:24.604Z","domain":"ads-api.twitter.com","root":"twitter.com","tracker":"twitter","type":"A","dnssec":false,"encrypted":false,"protocol":"UDP","clientIp":"2804:678c:c176:d500:bb43:b9d2:5d09:4def","status":"default","reasons":[]},{"timestamp":"2024-12-06T01:36:24.601Z","domain":"ads-api.twitter.com","root":"twitter.com","tracker":"twitter","type":"AAAA","dnssec":false,"encrypted":false,"protocol":"UDP","clientIp":"2804:678c:c176:d500:bb43:b9d2:5d09:4def","status":"default","reasons":[]},{"timestamp":"2024-12-06T01:36:24.575Z","domain":"analytics.twitter.com","root":"twitter.com","tracker":"twitter_analytics","type":"A","dnssec":false,"encrypted":false,"protocol":"UDP","clientIp":"2804:678c:c176:d500:bb43:b9d2:5d09:4def","status":"default","reasons":[]},{"timestamp":"2024-12-06T01:36:24.571Z","domain":"analytics.twitter.com","root":"twitter.com","tracker":"twitter_analytics","type":"AAAA","dnssec":false,"encrypted":false,"protocol":"UDP","clientIp":"2804:678c:c176:d500:bb43:b9d2:5d09:4def","status":"default","reasons":[]},{"timestamp":"2024-12-06T01:36:24.270Z","domain":"lh3.googleusercontent.com","root":"googleusercontent.com","tracker":"google_users","type":"A","dnssec":false,"encrypted":false,"protocol":"UDP","clientIp":"2804:678c:c176:d500:bb43:b9d2:5d09:4def","status":"default","reasons":[]},{"timestamp":"2024-12-06T01:36:24.268Z","domain":"lh3.googleusercontent.com","root":"googleusercontent.com","tracker":"google_users","type":"AAAA","dnssec":false,"encrypted":false,"protocol":"UDP","clientIp":"2804:678c:c176:d500:bb43:b9d2:5d09:4def","status":"default","reasons":[]},{"timestamp":"2024-12-06T01:36:23.804Z","domain":"api.x.com","root":"x.com","type":"A","dnssec":false,"encrypted":false,"protocol":"UDP","clientIp":"2804:678c:c176:d500:bb43:b9d2:5d09:4def","status":"default","reasons":[]},{"timestamp":"2024-12-06T01:36:23.804Z","domain":"t.co","root":"t.co","tracker":"twitter","type":"A","dnssec":false,"encrypted":false,"protocol":"UDP","clientIp":"2804:678c:c176:d500:bb43:b9d2:5d09:4def","status":"default","reasons":[]},{"timestamp":"2024-12-06T01:36:23.804Z","domain":"t.co","root":"t.co","tracker":"twitter","type":"AAAA","dnssec":false,"encrypted":false,"protocol":"UDP","clientIp":"2804:678c:c176:d500:bb43:b9d2:5d09:4def","status":"default","reasons":[]},{"timestamp":"2024-12-06T01:36:23.802Z","domain":"abs.twimg.com","root":"twimg.com","tracker":"twitter","type":"AAAA","dnssec":false,"encrypted":false,"protocol":"UDP","clientIp":"2804:678c:c176:d500:bb43:b9d2:5d09:4def","status":"default","reasons":[]},{"timestamp":"2024-12-06T01:36:23.802Z","domain":"abs.twimg.com","root":"twimg.com","tracker":"twitter","type":"A","dnssec":false,"encrypted":false,"protocol":"UDP","clientIp":"2804:678c:c176:d500:bb43:b9d2:5d09:4def","status":"default","reasons":[]},{"timestamp":"2024-12-06T01:36:23.801Z","domain":"api.x.com","root":"x.com","type":"AAAA","dnssec":false,"encrypted":false,"protocol":"UDP","clientIp":"2804:678c:c176:d500:bb43:b9d2:5d09:4def","status":"default","reasons":[]},{"timestamp":"2024-12-06T01:36:23.234Z","domain":"play-fe.googleapis.com","root":"play-fe.googleapis.com","tracker":"googleapis.com","type":"A","dnssec":false,"encrypted":false,"protocol":"UDP","clientIp":"2804:678c:c176:d500:bb43:b9d2:5d09:4def","status":"default","reasons":[]},{"timestamp":"2024-12-06T01:36:23.233Z","domain":"play-fe.googleapis.com","root":"play-fe.googleapis.com","tracker":"googleapis.com","type":"AAAA","dnssec":false,"encrypted":false,"protocol":"UDP","clientIp":"2804:678c:c176:d500:bb43:b9d2:5d09:4def","status":"default","reasons":[]},{"timestamp":"2024-12-06T01:36:23.167Z","domain":"twitter.com","root":"twitter.com","tracker":"twitter","type":"AAAA","dnssec":false,"encrypted":false,"protocol":"UDP","clientIp":"2804:678c:c176:d500:bb43:b9d2:5d09:4def","status":"default","reasons":[]},{"timestamp":"2024-12-06T01:36:23.167Z","domain":"twitter.com","root":"twitter.com","tracker":"twitter","type":"A","dnssec":false,"encrypted":false,"protocol":"UDP","clientIp":"2804:678c:c176:d500:bb43:b9d2:5d09:4def","status":"default","reasons":[]},{"timestamp":"2024-12-06T01:36:12.702Z","domain":"mobilemaps-pa-gz.googleapis.com","root":"mobilemaps-pa-gz.googleapis.com","tracker":"googleapis.com","type":"A","dnssec":false,"encrypted":false,"protocol":"UDP","clientIp":"2804:678c:c176:d500:bb43:b9d2:5d09:4def","status":"default","reasons":[]},{"timestamp":"2024-12-06T01:36:12.697Z","domain":"mobilemaps-pa-gz.googleapis.com","root":"mobilemaps-pa-gz.googleapis.com","tracker":"googleapis.com","type":"AAAA","dnssec":false,"encrypted":false,"protocol":"UDP","clientIp":"2804:678c:c176:d500:bb43:b9d2:5d09:4def","status":"default","reasons":[]},{"timestamp":"2024-12-06T01:36:07.980Z","domain":"inbox.google.com","root":"google.com","tracker":"google","type":"A","dnssec":false,"encrypted":false,"protocol":"UDP","clientIp":"2804:678c:c176:d500:bb43:b9d2:5d09:4def","status":"default","reasons":[]},{"timestamp":"2024-12-06T01:36:07.979Z","domain":"inbox.google.com","root":"google.com","tracker":"google","type":"AAAA","dnssec":false,"encrypted":false,"protocol":"UDP","clientIp":"2804:678c:c176:d500:bb43:b9d2:5d09:4def","status":"default","reasons":[]},{"timestamp":"2024-12-06T01:36:06.542Z","domain":"web.diagnostic.networking.aws.dev","root":"aws.dev","type":"A","dnssec":false,"encrypted":false,"protocol":"UDP","clientIp":"45.190.211.163","status":"default","reasons":[]},{"timestamp":"2024-12-06T01:36:02.754Z","domain":"b1.nel.goog","root":"nel.goog","type":"AAAA","dnssec":false,"encrypted":false,"protocol":"UDP","clientIp":"45.190.211.163","status":"default","reasons":[]},{"timestamp":"2024-12-06T01:36:02.754Z","domain":"b1.nel.goog","root":"nel.goog","type":"A","dnssec":false,"encrypted":false,"protocol":"UDP","clientIp":"45.190.211.163","status":"default","reasons":[]},{"timestamp":"2024-12-06T01:35:59.558Z","domain":"api.my.avira.com","root":"avira.com","type":"A","dnssec":false,"encrypted":false,"protocol":"UDP","clientIp":"2804:678c:c176:d500:bb43:b9d2:5d09:4def","status":"default","reasons":[]},{"timestamp":"2024-12-06T01:35:59.557Z","domain":"api.my.avira.com","root":"avira.com","type":"AAAA","dnssec":false,"encrypted":false,"protocol":"UDP","clientIp":"2804:678c:c176:d500:bb43:b9d2:5d09:4def","status":"default","reasons":[]},{"timestamp":"2024-12-06T01:35:58.076Z","domain":"ingress.eu1.rum-ingress-coralogix.com","root":"rum-ingress-coralogix.com","type":"HTTPS","dnssec":false,"encrypted":false,"protocol":"UDP","clientIp":"2804:678c:c176:d500:bb43:b9d2:5d09:4def","status":"default","reasons":[]},{"timestamp":"2024-12-06T01:35:58.076Z","domain":"ingress.eu1.rum-ingress-coralogix.com","root":"rum-ingress-coralogix.com","type":"A","dnssec":false,"encrypted":false,"protocol":"UDP","clientIp":"2804:678c:c176:d500:bb43:b9d2:5d09:4def","status":"default","reasons":[]},{"timestamp":"2024-12-06T01:35:58.075Z","domain":"ingress.eu1.rum-ingress-coralogix.com","root":"rum-ingress-coralogix.com","type":"AAAA","dnssec":false,"encrypted":false,"protocol":"UDP","clientIp":"2804:678c:c176:d500:bb43:b9d2:5d09:4def","status":"default","reasons":[]},{"timestamp":"2024-12-06T01:35:30.986Z","domain":"fonts.googleapis.com","root":"fonts.googleapis.com","tracker":"google_fonts","type":"A","dnssec":false,"encrypted":false,"protocol":"UDP","clientIp":"2804:678c:c176:d500:bb43:b9d2:5d09:4def","status":"default","reasons":[]},{"timestamp":"2024-12-06T01:35:30.986Z","domain":"cdn-f.adsmoloco.com","root":"adsmoloco.com","type":"A","dnssec":false,"encrypted":false,"protocol":"UDP","clientIp":"2804:678c:c176:d500:bb43:b9d2:5d09:4def","status":"default","reasons":[]},{"timestamp":"2024-12-06T01:35:30.985Z","domain":"fonts.gstatic.com","root":"gstatic.com","tracker":"gstatic","type":"A","dnssec":false,"encrypted":false,"protocol":"UDP","clientIp":"2804:678c:c176:d500:bb43:b9d2:5d09:4def","status":"default","reasons":[]},{"timestamp":"2024-12-06T01:35:30.980Z","domain":"fonts.googleapis.com","root":"fonts.googleapis.com","tracker":"google_fonts","type":"AAAA","dnssec":false,"encrypted":false,"protocol":"UDP","clientIp":"2804:678c:c176:d500:bb43:b9d2:5d09:4def","status":"default","reasons":[]},{"timestamp":"2024-12-06T01:35:30.980Z","domain":"fonts.gstatic.com","root":"gstatic.com","tracker":"gstatic","type":"AAAA","dnssec":false,"encrypted":false,"protocol":"UDP","clientIp":"2804:678c:c176:d500:bb43:b9d2:5d09:4def","status":"default","reasons":[]},{"timestamp":"2024-12-06T01:35:30.869Z","domain":"google-ohttp-relay-safebrowsing.fastly-edge.com","root":"google-ohttp-relay-safebrowsing.fastly-edge.com","type":"A","dnssec":false,"encrypted":false,"protocol":"UDP","clientIp":"2804:678c:c176:d500:bb43:b9d2:5d09:4def","status":"default","reasons":[]},{"timestamp":"2024-12-06T01:35:30.869Z","domain":"google-ohttp-relay-safebrowsing.fastly-edge.com","root":"google-ohttp-relay-safebrowsing.fastly-edge.com","type":"AAAA","dnssec":false,"encrypted":false,"protocol":"UDP","clientIp":"2804:678c:c176:d500:bb43:b9d2:5d09:4def","status":"default","reasons":[]},{"timestamp":"2024-12-06T01:35:30.038Z","domain":"content-autofill.googleapis.com","root":"content-autofill.googleapis.com","tracker":"googleapis.com","type":"HTTPS","dnssec":false,"encrypted":false,"protocol":"UDP","clientIp":"2804:678c:c176:d500:bb43:b9d2:5d09:4def","status":"default","reasons":[]},{"timestamp":"2024-12-06T01:35:30.038Z","domain":"content-autofill.googleapis.com","root":"content-autofill.googleapis.com","tracker":"googleapis.com","type":"A","dnssec":false,"encrypted":false,"protocol":"UDP","clientIp":"2804:678c:c176:d500:bb43:b9d2:5d09:4def","status":"default","reasons":[]},{"timestamp":"2024-12-06T01:35:30.037Z","domain":"content-autofill.googleapis.com","root":"content-autofill.googleapis.com","tracker":"googleapis.com","type":"AAAA","dnssec":false,"encrypted":false,"protocol":"UDP","clientIp":"2804:678c:c176:d500:bb43:b9d2:5d09:4def","status":"default","reasons":[]},{"timestamp":"2024-12-06T01:35:29.966Z","domain":"pagead2.googlesyndication.com","root":"googlesyndication.com","tracker":"google_syndication","type":"A","dnssec":false,"encrypted":false,"protocol":"UDP","clientIp":"2804:678c:c176:d500:bb43:b9d2:5d09:4def","status":"default","reasons":[]},{"timestamp":"2024-12-06T01:35:29.966Z","domain":"pagead2.googlesyndication.com","root":"googlesyndication.com","tracker":"google_syndication","type":"AAAA","dnssec":false,"encrypted":false,"protocol":"UDP","clientIp":"2804:678c:c176:d500:bb43:b9d2:5d09:4def","status":"default","reasons":[]},{"timestamp":"2024-12-06T01:35:29.942Z","domain":"video.twimg.com","root":"twimg.com","tracker":"twitter","type":"A","dnssec":false,"encrypted":false,"protocol":"UDP","clientIp":"2804:678c:c176:d500:bb43:b9d2:5d09:4def","status":"default","reasons":[]},{"timestamp":"2024-12-06T01:35:29.941Z","domain":"video.twimg.com","root":"twimg.com","tracker":"twitter","type":"AAAA","dnssec":false,"encrypted":false,"protocol":"UDP","clientIp":"2804:678c:c176:d500:bb43:b9d2:5d09:4def","status":"default","reasons":[]},{"timestamp":"2024-12-06T01:35:29.935Z","domain":"pbs.twimg.com","root":"twimg.com","tracker":"twitter","type":"AAAA","dnssec":false,"encrypted":false,"protocol":"UDP","clientIp":"2804:678c:c176:d500:bb43:b9d2:5d09:4def","status":"default","reasons":[]},{"timestamp":"2024-12-06T01:35:29.928Z","domain":"pbs.twimg.com","root":"twimg.com","tracker":"twitter","type":"A","dnssec":false,"encrypted":false,"protocol":"UDP","clientIp":"2804:678c:c176:d500:bb43:b9d2:5d09:4def","status":"default","reasons":[]},{"timestamp":"2024-12-06T01:35:29.717Z","domain":"pubads.g.doubleclick.net","root":"doubleclick.net","tracker":"doubleclick","type":"A","dnssec":false,"encrypted":false,"protocol":"UDP","clientIp":"2804:678c:c176:d500:bb43:b9d2:5d09:4def","status":"default","reasons":[]},{"timestamp":"2024-12-06T01:35:29.717Z","domain":"pubads.g.doubleclick.net","root":"doubleclick.net","tracker":"doubleclick","type":"AAAA","dnssec":false,"encrypted":false,"protocol":"UDP","clientIp":"2804:678c:c176:d500:bb43:b9d2:5d09:4def","status":"default","reasons":[]},{"timestamp":"2024-12-06T01:35:29.325Z","domain":"www.linkedin.com","root":"linkedin.com","tracker":"linkedin","type":"AAAA","dnssec":false,"encrypted":false,"protocol":"UDP","clientIp":"2804:678c:c176:d500:bb43:b9d2:5d09:4def","status":"default","reasons":[]},{"timestamp":"2024-12-06T01:35:29.325Z","domain":"www.linkedin.com","root":"linkedin.com","tracker":"linkedin","type":"A","dnssec":false,"encrypted":false,"protocol":"UDP","clientIp":"2804:678c:c176:d500:bb43:b9d2:5d09:4def","status":"default","reasons":[]},{"timestamp":"2024-12-06T01:35:29.010Z","domain":"video-edge-2b0ff7.pdx01.abs.hls.ttvnw.net","root":"ttvnw.net","tracker":"twitch_cdn","type":"A","dnssec":false,"encrypted":false,"protocol":"UDP","clientIp":"2804:678c:c176:d500:bb43:b9d2:5d09:4def","status":"default","reasons":[]},{"timestamp":"2024-12-06T01:35:29.009Z","domain":"video-edge-2b0ff7.pdx01.abs.hls.ttvnw.net","root":"ttvnw.net","tracker":"twitch_cdn","type":"AAAA","dnssec":false,"encrypted":false,"protocol":"UDP","clientIp":"2804:678c:c176:d500:bb43:b9d2:5d09:4def","status":"default","reasons":[]},{"timestamp":"2024-12-06T01:35:28.881Z","domain":"sdkconfig.intl.xiaomi.com","root":"xiaomi.com","type":"A","dnssec":false,"encrypted":false,"protocol":"UDP","clientIp":"2804:678c:c176:d500:d47:6f35:ada:bde0","status":"default","reasons":[]},{"timestamp":"2024-12-06T01:35:28.878Z","domain":"sdkconfig.intl.xiaomi.com","root":"xiaomi.com","type":"AAAA","dnssec":false,"encrypted":false,"protocol":"UDP","clientIp":"2804:678c:c176:d500:d47:6f35:ada:bde0","status":"default","reasons":[]},{"timestamp":"2024-12-06T01:35:24.637Z","domain":"www.googleoptimize.com","root":"googleoptimize.com","type":"HTTPS","dnssec":false,"encrypted":false,"protocol":"UDP","clientIp":"2804:678c:c176:d500:bb43:b9d2:5d09:4def","status":"default","reasons":[]},{"timestamp":"2024-12-06T01:35:24.636Z","domain":"www.googleoptimize.com","root":"googleoptimize.com","type":"AAAA","dnssec":false,"encrypted":false,"protocol":"UDP","clientIp":"2804:678c:c176:d500:bb43:b9d2:5d09:4def","status":"default","reasons":[]},{"timestamp":"2024-12-06T01:35:24.636Z","domain":"www.googleoptimize.com","root":"googleoptimize.com","type":"A","dnssec":false,"encrypted":false,"protocol":"UDP","clientIp":"2804:678c:c176:d500:bb43:b9d2:5d09:4def","status":"default","reasons":[]},{"timestamp":"2024-12-06T01:35:24.218Z","domain":"acsbace.com","root":"acsbace.com","type":"AAAA","dnssec":false,"encrypted":false,"protocol":"UDP","clientIp":"2804:678c:c176:d500:bb43:b9d2:5d09:4def","status":"default","reasons":[]},{"timestamp":"2024-12-06T01:35:24.218Z","domain":"acsbace.com","root":"acsbace.com","type":"A","dnssec":false,"encrypted":false,"protocol":"UDP","clientIp":"2804:678c:c176:d500:bb43:b9d2:5d09:4def","status":"default","reasons":[]},{"timestamp":"2024-12-06T01:35:24.218Z","domain":"acsbace.com","root":"acsbace.com","type":"HTTPS","dnssec":false,"encrypted":false,"protocol":"UDP","clientIp":"2804:678c:c176:d500:bb43:b9d2:5d09:4def","status":"default","reasons":[]},{"timestamp":"2024-12-06T01:35:13.490Z","domain":"optimizationguide-pa.googleapis.com","root":"optimizationguide-pa.googleapis.com","tracker":"googleapis.com","type":"A","dnssec":false,"encrypted":false,"protocol":"UDP","clientIp":"2804:678c:c176:d500:bb43:b9d2:5d09:4def","status":"default","reasons":[]},{"timestamp":"2024-12-06T01:35:13.490Z","domain":"optimizationguide-pa.googleapis.com","root":"optimizationguide-pa.googleapis.com","tracker":"googleapis.com","type":"AAAA","dnssec":false,"encrypted":false,"protocol":"UDP","clientIp":"2804:678c:c176:d500:bb43:b9d2:5d09:4def","status":"default","reasons":[]},{"timestamp":"2024-12-06T01:35:13.490Z","domain":"optimizationguide-pa.googleapis.com","root":"optimizationguide-pa.googleapis.com","tracker":"googleapis.com","type":"HTTPS","dnssec":false,"encrypted":false,"protocol":"UDP","clientIp":"2804:678c:c176:d500:bb43:b9d2:5d09:4def","status":"default","reasons":[]},{"timestamp":"2024-12-06T01:35:07.648Z","domain":"events.launchdarkly.com","root":"launchdarkly.com","tracker":"launch_darkly","type":"HTTPS","dnssec":false,"encrypted":false,"protocol":"UDP","clientIp":"2804:678c:c176:d500:bb43:b9d2:5d09:4def","status":"default","reasons":[]},{"timestamp":"2024-12-06T01:35:07.647Z","domain":"events.launchdarkly.com","root":"launchdarkly.com","tracker":"launch_darkly","type":"AAAA","dnssec":false,"encrypted":false,"protocol":"UDP","clientIp":"2804:678c:c176:d500:bb43:b9d2:5d09:4def","status":"default","reasons":[]},{"timestamp":"2024-12-06T01:35:07.647Z","domain":"events.launchdarkly.com","root":"launchdarkly.com","tracker":"launch_darkly","type":"A","dnssec":false,"encrypted":false,"protocol":"UDP","clientIp":"2804:678c:c176:d500:bb43:b9d2:5d09:4def","status":"default","reasons":[]},{"timestamp":"2024-12-06T01:35:06.004Z","domain":"clientstream.launchdarkly.com","root":"launchdarkly.com","type":"HTTPS","dnssec":false,"encrypted":false,"protocol":"UDP","clientIp":"2804:678c:c176:d500:bb43:b9d2:5d09:4def","status":"default","reasons":[]},{"timestamp":"2024-12-06T01:35:06.003Z","domain":"clientstream.launchdarkly.com","root":"launchdarkly.com","type":"A","dnssec":false,"encrypted":false,"protocol":"UDP","clientIp":"2804:678c:c176:d500:bb43:b9d2:5d09:4def","status":"default","reasons":[]},{"timestamp":"2024-12-06T01:35:06.003Z","domain":"clientstream.launchdarkly.com","root":"launchdarkly.com","type":"AAAA","dnssec":false,"encrypted":false,"protocol":"UDP","clientIp":"2804:678c:c176:d500:bb43:b9d2:5d09:4def","status":"default","reasons":[]},{"timestamp":"2024-12-06T01:35:05.961Z","domain":"app.launchdarkly.com","root":"launchdarkly.com","type":"A","dnssec":false,"encrypted":false,"protocol":"UDP","clientIp":"2804:678c:c176:d500:bb43:b9d2:5d09:4def","status":"default","reasons":[]},{"timestamp":"2024-12-06T01:35:05.960Z","domain":"app.launchdarkly.com","root":"launchdarkly.com","type":"AAAA","dnssec":false,"encrypted":false,"protocol":"UDP","clientIp":"2804:678c:c176:d500:bb43:b9d2:5d09:4def","status":"default","reasons":[]},{"timestamp":"2024-12-06T01:35:05.960Z","domain":"app.launchdarkly.com","root":"launchdarkly.com","type":"HTTPS","dnssec":false,"encrypted":false,"protocol":"UDP","clientIp":"2804:678c:c176:d500:bb43:b9d2:5d09:4def","status":"default","reasons":[]},{"timestamp":"2024-12-06T01:35:04.832Z","domain":"accessibe.zendesk.com","root":"zendesk.com","tracker":"zendesk","type":"HTTPS","dnssec":false,"encrypted":false,"protocol":"UDP","clientIp":"2804:678c:c176:d500:bb43:b9d2:5d09:4def","status":"default","reasons":[]},{"timestamp":"2024-12-06T01:35:04.832Z","domain":"accessibe.zendesk.com","root":"zendesk.com","tracker":"zendesk","type":"A","dnssec":false,"encrypted":false,"protocol":"UDP","clientIp":"2804:678c:c176:d500:bb43:b9d2:5d09:4def","status":"default","reasons":[]},{"timestamp":"2024-12-06T01:35:04.831Z","domain":"accessibe.zendesk.com","root":"zendesk.com","tracker":"zendesk","type":"AAAA","dnssec":false,"encrypted":false,"protocol":"UDP","clientIp":"2804:678c:c176:d500:bb43:b9d2:5d09:4def","status":"default","reasons":[]},{"timestamp":"2024-12-06T01:35:02.884Z","domain":"ap-gue1.spotify.com","root":"spotify.com","tracker":"spotify","type":"A","dnssec":false,"encrypted":false,"protocol":"UDP","clientIp":"45.190.211.163","status":"default","reasons":[]},{"timestamp":"2024-12-06T01:35:02.750Z","domain":"b1.nel.goog","root":"nel.goog","type":"HTTPS","dnssec":false,"encrypted":false,"protocol":"UDP","clientIp":"45.190.211.163","status":"default","reasons":[]},{"timestamp":"2024-12-06T01:35:02.749Z","domain":"b1.nel.goog","root":"nel.goog","type":"A","dnssec":false,"encrypted":false,"protocol":"UDP","clientIp":"45.190.211.163","status":"default","reasons":[]},{"timestamp":"2024-12-06T01:35:02.749Z","domain":"b1.nel.goog","root":"nel.goog","type":"AAAA","dnssec":false,"encrypted":false,"protocol":"UDP","clientIp":"45.190.211.163","status":"default","reasons":[]},{"timestamp":"2024-12-06T01:35:02.661Z","domain":"apresolve.spotify.com","root":"spotify.com","tracker":"spotify","type":"A","dnssec":false,"encrypted":false,"protocol":"UDP","clientIp":"45.190.211.163","status":"default","reasons":[]}],"meta":{"pagination":{"cursor":"64vk6ctm6gw3jc1j6rv32"},"stream":{"id":"64vk6ctm6gwk0chm6cu3a"}}}