{"data":[{"timestamp":"2024-11-23T01:21:36.456Z","domain":"gateway-copilot.bingviz.microsoftapp.net","root":"microsoftapp.net","type":"AAAA","dnssec":false,"encrypted":false,"protocol":"UDP","clientIp":"2804:678c:c176:d500:d47:6f35:ada:bde0","status":"default","reasons":[]},{"timestamp":"2024-11-23T01:21:36.456Z","domain":"gateway-copilot.bingviz.microsoftapp.net","root":"microsoftapp.net","type":"A","dnssec":false,"encrypted":false,"protocol":"UDP","clientIp":"2804:678c:c176:d500:d47:6f35:ada:bde0","status":"default","reasons":[]},{"timestamp":"2024-11-23T01:21:33.023Z","domain":"avs-alexa-14-na.amazon.com","root":"amazon.com","tracker":"amazon","type":"A","dnssec":false,"encrypted":false,"protocol":"UDP","clientIp":"45.190.211.150","status":"default","reasons":[]},{"timestamp":"2024-11-23T01:21:33.011Z","domain":"avs-alexa-14-na.amazon.com","root":"amazon.com","tracker":"amazon","type":"A","dnssec":false,"encrypted":false,"protocol":"UDP","clientIp":"45.190.211.150","status":"default","reasons":[]},{"timestamp":"2024-11-23T01:21:20.721Z","domain":"chat-e2ee-mini.facebook.com","root":"facebook.com","tracker":"facebook","type":"A","dnssec":false,"encrypted":false,"protocol":"UDP","clientIp":"2804:678c:c176:d500:d47:6f35:ada:bde0","status":"default","reasons":[]},{"timestamp":"2024-11-23T01:21:20.719Z","domain":"chat-e2ee-mini.facebook.com","root":"facebook.com","tracker":"facebook","type":"AAAA","dnssec":false,"encrypted":false,"protocol":"UDP","clientIp":"2804:678c:c176:d500:d47:6f35:ada:bde0","status":"default","reasons":[]},{"timestamp":"2024-11-23T01:21:20.048Z","domain":"edge-mqtt.facebook.com","root":"facebook.com","tracker":"facebook","type":"A","dnssec":false,"encrypted":false,"protocol":"UDP","clientIp":"2804:678c:c176:d500:d47:6f35:ada:bde0","status":"default","reasons":[]},{"timestamp":"2024-11-23T01:21:20.046Z","domain":"edge-mqtt.facebook.com","root":"facebook.com","tracker":"facebook","type":"AAAA","dnssec":false,"encrypted":false,"protocol":"UDP","clientIp":"2804:678c:c176:d500:d47:6f35:ada:bde0","status":"default","reasons":[]},{"timestamp":"2024-11-23T01:21:19.840Z","domain":"gateway.facebook.com","root":"facebook.com","tracker":"facebook","type":"AAAA","dnssec":false,"encrypted":false,"protocol":"UDP","clientIp":"2804:678c:c176:d500:d47:6f35:ada:bde0","status":"default","reasons":[]},{"timestamp":"2024-11-23T01:21:19.834Z","domain":"gateway.facebook.com","root":"facebook.com","tracker":"facebook","type":"A","dnssec":false,"encrypted":false,"protocol":"UDP","clientIp":"2804:678c:c176:d500:d47:6f35:ada:bde0","status":"default","reasons":[]},{"timestamp":"2024-11-23T01:21:18.894Z","domain":"notifications-pa.googleapis.com","root":"notifications-pa.googleapis.com","tracker":"googleapis.com","type":"AAAA","dnssec":false,"encrypted":false,"protocol":"UDP","clientIp":"2804:678c:c176:d500:d47:6f35:ada:bde0","status":"default","reasons":[]},{"timestamp":"2024-11-23T01:21:18.894Z","domain":"notifications-pa.googleapis.com","root":"notifications-pa.googleapis.com","tracker":"googleapis.com","type":"A","dnssec":false,"encrypted":false,"protocol":"UDP","clientIp":"2804:678c:c176:d500:d47:6f35:ada:bde0","status":"default","reasons":[]},{"timestamp":"2024-11-23T01:21:09.362Z","domain":"graph.facebook.com","root":"facebook.com","tracker":"facebook_graph","type":"A","dnssec":false,"encrypted":false,"protocol":"UDP","clientIp":"2804:678c:c176:d500:d47:6f35:ada:bde0","status":"default","reasons":[]},{"timestamp":"2024-11-23T01:21:09.359Z","domain":"graph.facebook.com","root":"facebook.com","tracker":"facebook_graph","type":"AAAA","dnssec":false,"encrypted":false,"protocol":"UDP","clientIp":"2804:678c:c176:d500:d47:6f35:ada:bde0","status":"default","reasons":[]},{"timestamp":"2024-11-23T01:21:09.272Z","domain":"api.facebook.com","root":"facebook.com","tracker":"facebook","type":"A","dnssec":false,"encrypted":false,"protocol":"UDP","clientIp":"2804:678c:c176:d500:d47:6f35:ada:bde0","status":"default","reasons":[]},{"timestamp":"2024-11-23T01:21:09.272Z","domain":"api.facebook.com","root":"facebook.com","tracker":"facebook","type":"AAAA","dnssec":false,"encrypted":false,"protocol":"UDP","clientIp":"2804:678c:c176:d500:d47:6f35:ada:bde0","status":"default","reasons":[]},{"timestamp":"2024-11-23T01:21:09.187Z","domain":"b-api.facebook.com","root":"facebook.com","tracker":"facebook","type":"AAAA","dnssec":false,"encrypted":false,"protocol":"UDP","clientIp":"2804:678c:c176:d500:d47:6f35:ada:bde0","status":"default","reasons":[]},{"timestamp":"2024-11-23T01:21:09.187Z","domain":"b-api.facebook.com","root":"facebook.com","tracker":"facebook","type":"A","dnssec":false,"encrypted":false,"protocol":"UDP","clientIp":"2804:678c:c176:d500:d47:6f35:ada:bde0","status":"default","reasons":[]},{"timestamp":"2024-11-23T01:21:06.082Z","domain":"weatherapi.intl.xiaomi.com","root":"xiaomi.com","type":"A","dnssec":false,"encrypted":false,"protocol":"UDP","clientIp":"2804:678c:c176:d500:e18f:7ae:e449:180a","status":"default","reasons":[]},{"timestamp":"2024-11-23T01:21:06.078Z","domain":"weatherapi.intl.xiaomi.com","root":"xiaomi.com","type":"AAAA","dnssec":false,"encrypted":false,"protocol":"UDP","clientIp":"2804:678c:c176:d500:e18f:7ae:e449:180a","status":"default","reasons":[]},{"timestamp":"2024-11-23T01:21:03.447Z","domain":"googlehomefoyer-pa.googleapis.com","root":"googlehomefoyer-pa.googleapis.com","tracker":"googleapis.com","type":"A","dnssec":false,"encrypted":false,"protocol":"UDP","clientIp":"2804:678c:c176:d500:d47:6f35:ada:bde0","status":"default","reasons":[]},{"timestamp":"2024-11-23T01:21:03.446Z","domain":"googlehomefoyer-pa.googleapis.com","root":"googlehomefoyer-pa.googleapis.com","tracker":"googleapis.com","type":"AAAA","dnssec":false,"encrypted":false,"protocol":"UDP","clientIp":"2804:678c:c176:d500:d47:6f35:ada:bde0","status":"default","reasons":[]},{"timestamp":"2024-11-23T01:21:02.709Z","domain":"youtubei.googleapis.com","root":"youtubei.googleapis.com","tracker":"googleapis.com","type":"A","dnssec":false,"encrypted":false,"protocol":"UDP","clientIp":"2804:678c:c176:d500:d47:6f35:ada:bde0","status":"default","reasons":[]},{"timestamp":"2024-11-23T01:21:02.708Z","domain":"youtubei.googleapis.com","root":"youtubei.googleapis.com","tracker":"googleapis.com","type":"AAAA","dnssec":false,"encrypted":false,"protocol":"UDP","clientIp":"2804:678c:c176:d500:d47:6f35:ada:bde0","status":"default","reasons":[]},{"timestamp":"2024-11-23T01:21:02.538Z","domain":"photosdata-pa.googleapis.com","root":"photosdata-pa.googleapis.com","tracker":"googleapis.com","type":"A","dnssec":false,"encrypted":false,"protocol":"UDP","clientIp":"2804:678c:c176:d500:d47:6f35:ada:bde0","status":"default","reasons":[]},{"timestamp":"2024-11-23T01:21:02.534Z","domain":"photosdata-pa.googleapis.com","root":"photosdata-pa.googleapis.com","tracker":"googleapis.com","type":"AAAA","dnssec":false,"encrypted":false,"protocol":"UDP","clientIp":"2804:678c:c176:d500:d47:6f35:ada:bde0","status":"default","reasons":[]},{"timestamp":"2024-11-23T01:21:02.476Z","domain":"lh4.googleusercontent.com","root":"googleusercontent.com","tracker":"google_users","type":"A","dnssec":false,"encrypted":false,"protocol":"UDP","clientIp":"2804:678c:c176:d500:d47:6f35:ada:bde0","status":"default","reasons":[]},{"timestamp":"2024-11-23T01:21:02.473Z","domain":"lh4.googleusercontent.com","root":"googleusercontent.com","tracker":"google_users","type":"AAAA","dnssec":false,"encrypted":false,"protocol":"UDP","clientIp":"2804:678c:c176:d500:d47:6f35:ada:bde0","status":"default","reasons":[]},{"timestamp":"2024-11-23T01:21:01.991Z","domain":"app-measurement.com","root":"app-measurement.com","type":"AAAA","dnssec":false,"encrypted":false,"protocol":"UDP","clientIp":"2804:678c:c176:d500:d47:6f35:ada:bde0","status":"default","reasons":[]},{"timestamp":"2024-11-23T01:21:01.991Z","domain":"app-measurement.com","root":"app-measurement.com","type":"A","dnssec":false,"encrypted":false,"protocol":"UDP","clientIp":"2804:678c:c176:d500:d47:6f35:ada:bde0","status":"default","reasons":[]},{"timestamp":"2024-11-23T01:21:01.990Z","domain":"android.googleapis.com","root":"android.googleapis.com","tracker":"googleapis.com","type":"A","dnssec":false,"encrypted":false,"protocol":"UDP","clientIp":"2804:678c:c176:d500:d47:6f35:ada:bde0","status":"default","reasons":[]},{"timestamp":"2024-11-23T01:21:01.990Z","domain":"android.googleapis.com","root":"android.googleapis.com","tracker":"googleapis.com","type":"AAAA","dnssec":false,"encrypted":false,"protocol":"UDP","clientIp":"2804:678c:c176:d500:d47:6f35:ada:bde0","status":"default","reasons":[]},{"timestamp":"2024-11-23T01:20:14.032Z","domain":"api-30-0-0.twitter.com","root":"twitter.com","tracker":"twitter","type":"A","dnssec":false,"encrypted":false,"protocol":"UDP","clientIp":"2804:678c:c176:d500:d47:6f35:ada:bde0","status":"default","reasons":[]},{"timestamp":"2024-11-23T01:20:14.029Z","domain":"api-30-0-0.twitter.com","root":"twitter.com","tracker":"twitter","type":"AAAA","dnssec":false,"encrypted":false,"protocol":"UDP","clientIp":"2804:678c:c176:d500:d47:6f35:ada:bde0","status":"default","reasons":[]},{"timestamp":"2024-11-23T01:20:14.007Z","domain":"api-0-4-6.twitter.com","root":"twitter.com","tracker":"twitter","type":"AAAA","dnssec":false,"encrypted":false,"protocol":"UDP","clientIp":"2804:678c:c176:d500:d47:6f35:ada:bde0","status":"default","reasons":[]},{"timestamp":"2024-11-23T01:20:13.932Z","domain":"api-0-4-3.twitter.com","root":"twitter.com","tracker":"twitter","type":"AAAA","dnssec":false,"encrypted":false,"protocol":"UDP","clientIp":"2804:678c:c176:d500:d47:6f35:ada:bde0","status":"default","reasons":[]},{"timestamp":"2024-11-23T01:20:11.639Z","domain":"s.youtube.com","root":"youtube.com","tracker":"youtube","type":"A","dnssec":false,"encrypted":false,"protocol":"UDP","clientIp":"2804:678c:c176:d500:d47:6f35:ada:bde0","status":"default","reasons":[]},{"timestamp":"2024-11-23T01:20:11.639Z","domain":"s.youtube.com","root":"youtube.com","tracker":"youtube","type":"AAAA","dnssec":false,"encrypted":false,"protocol":"UDP","clientIp":"2804:678c:c176:d500:d47:6f35:ada:bde0","status":"default","reasons":[]},{"timestamp":"2024-11-23T01:20:08.590Z","domain":"pdx-api.twitter.com","root":"twitter.com","tracker":"twitter","type":"A","dnssec":false,"encrypted":false,"protocol":"UDP","clientIp":"2804:678c:c176:d500:d47:6f35:ada:bde0","status":"default","reasons":[]},{"timestamp":"2024-11-23T01:20:07.190Z","domain":"sb.scorecardresearch.com","root":"scorecardresearch.com","tracker":"scorecard_research_beacon","type":"A","dnssec":false,"encrypted":false,"protocol":"UDP","clientIp":"2804:678c:c176:d500:d47:6f35:ada:bde0","status":"default","reasons":[]},{"timestamp":"2024-11-23T01:20:06.812Z","domain":"browser-intake-datadoghq.com","root":"browser-intake-datadoghq.com","type":"A","dnssec":false,"encrypted":false,"protocol":"UDP","clientIp":"2804:678c:c176:d500:d47:6f35:ada:bde0","status":"default","reasons":[]},{"timestamp":"2024-11-23T01:20:06.810Z","domain":"browser-intake-datadoghq.com","root":"browser-intake-datadoghq.com","type":"AAAA","dnssec":false,"encrypted":false,"protocol":"UDP","clientIp":"2804:678c:c176:d500:d47:6f35:ada:bde0","status":"default","reasons":[]},{"timestamp":"2024-11-23T01:20:06.514Z","domain":"assets.adobedtm.com","root":"adobedtm.com","tracker":"adobe_dynamic_tag_management","type":"A","dnssec":false,"encrypted":false,"protocol":"UDP","clientIp":"2804:678c:c176:d500:d47:6f35:ada:bde0","status":"default","reasons":[]},{"timestamp":"2024-11-23T01:20:06.509Z","domain":"assets.adobedtm.com","root":"adobedtm.com","tracker":"adobe_dynamic_tag_management","type":"AAAA","dnssec":false,"encrypted":false,"protocol":"UDP","clientIp":"2804:678c:c176:d500:d47:6f35:ada:bde0","status":"default","reasons":[]},{"timestamp":"2024-11-23T01:20:05.550Z","domain":"firebaselogging.googleapis.com","root":"firebaselogging.googleapis.com","tracker":"googleapis.com","type":"A","dnssec":false,"encrypted":false,"protocol":"UDP","clientIp":"2804:678c:c176:d500:d47:6f35:ada:bde0","status":"default","reasons":[]},{"timestamp":"2024-11-23T01:20:05.534Z","domain":"firebaselogging.googleapis.com","root":"firebaselogging.googleapis.com","tracker":"googleapis.com","type":"AAAA","dnssec":false,"encrypted":false,"protocol":"UDP","clientIp":"2804:678c:c176:d500:d47:6f35:ada:bde0","status":"default","reasons":[]},{"timestamp":"2024-11-23T01:19:59.485Z","domain":"api.fstr.rocks","root":"fstr.rocks","type":"A","dnssec":false,"encrypted":false,"protocol":"UDP","clientIp":"2804:678c:c176:d500:d47:6f35:ada:bde0","status":"default","reasons":[]},{"timestamp":"2024-11-23T01:19:59.484Z","domain":"api.fstr.rocks","root":"fstr.rocks","type":"AAAA","dnssec":false,"encrypted":false,"protocol":"UDP","clientIp":"2804:678c:c176:d500:d47:6f35:ada:bde0","status":"default","reasons":[]},{"timestamp":"2024-11-23T01:19:52.963Z","domain":"android.clients.google.com","root":"google.com","tracker":"google","type":"A","dnssec":false,"encrypted":false,"protocol":"UDP","clientIp":"2804:678c:c176:d500:d47:6f35:ada:bde0","status":"default","reasons":[]},{"timestamp":"2024-11-23T01:19:52.961Z","domain":"android.clients.google.com","root":"google.com","tracker":"google","type":"AAAA","dnssec":false,"encrypted":false,"protocol":"UDP","clientIp":"2804:678c:c176:d500:d47:6f35:ada:bde0","status":"default","reasons":[]},{"timestamp":"2024-11-23T01:19:51.868Z","domain":"graph.instagram.com","root":"instagram.com","tracker":"instagram_com","type":"A","dnssec":false,"encrypted":false,"protocol":"UDP","clientIp":"2804:678c:c176:d500:d47:6f35:ada:bde0","status":"default","reasons":[]},{"timestamp":"2024-11-23T01:19:51.867Z","domain":"graph.instagram.com","root":"instagram.com","tracker":"instagram_com","type":"AAAA","dnssec":false,"encrypted":false,"protocol":"UDP","clientIp":"2804:678c:c176:d500:d47:6f35:ada:bde0","status":"default","reasons":[]},{"timestamp":"2024-11-23T01:19:51.202Z","domain":"i.instagram.com","root":"instagram.com","tracker":"instagram_com","type":"A","dnssec":false,"encrypted":false,"protocol":"UDP","clientIp":"2804:678c:c176:d500:d47:6f35:ada:bde0","status":"default","reasons":[]},{"timestamp":"2024-11-23T01:19:51.201Z","domain":"i.instagram.com","root":"instagram.com","tracker":"instagram_com","type":"A","dnssec":false,"encrypted":false,"protocol":"UDP","clientIp":"2804:678c:c176:d500:d47:6f35:ada:bde0","status":"default","reasons":[]},{"timestamp":"2024-11-23T01:19:51.197Z","domain":"i.instagram.com","root":"instagram.com","tracker":"instagram_com","type":"AAAA","dnssec":false,"encrypted":false,"protocol":"UDP","clientIp":"2804:678c:c176:d500:d47:6f35:ada:bde0","status":"default","reasons":[]},{"timestamp":"2024-11-23T01:19:45.355Z","domain":"login.microsoftonline.com","root":"microsoftonline.com","tracker":"microsoft","type":"A","dnssec":false,"encrypted":false,"protocol":"UDP","clientIp":"2804:678c:c176:d500:d47:6f35:ada:bde0","status":"default","reasons":[]},{"timestamp":"2024-11-23T01:19:45.353Z","domain":"login.microsoftonline.com","root":"microsoftonline.com","tracker":"microsoft","type":"AAAA","dnssec":false,"encrypted":false,"protocol":"UDP","clientIp":"2804:678c:c176:d500:d47:6f35:ada:bde0","status":"default","reasons":[]},{"timestamp":"2024-11-23T01:19:44.882Z","domain":"my.microsoftpersonalcontent.com","root":"microsoftpersonalcontent.com","type":"A","dnssec":false,"encrypted":false,"protocol":"UDP","clientIp":"2804:678c:c176:d500:d47:6f35:ada:bde0","status":"default","reasons":[]},{"timestamp":"2024-11-23T01:19:44.878Z","domain":"my.microsoftpersonalcontent.com","root":"microsoftpersonalcontent.com","type":"AAAA","dnssec":false,"encrypted":false,"protocol":"UDP","clientIp":"2804:678c:c176:d500:d47:6f35:ada:bde0","status":"default","reasons":[]},{"timestamp":"2024-11-23T01:19:44.318Z","domain":"skyapi.policies.live.net","root":"live.net","type":"A","dnssec":false,"encrypted":false,"protocol":"UDP","clientIp":"2804:678c:c176:d500:d47:6f35:ada:bde0","status":"default","reasons":[]},{"timestamp":"2024-11-23T01:19:44.313Z","domain":"skyapi.policies.live.net","root":"live.net","type":"AAAA","dnssec":false,"encrypted":false,"protocol":"UDP","clientIp":"2804:678c:c176:d500:d47:6f35:ada:bde0","status":"default","reasons":[]},{"timestamp":"2024-11-23T01:19:43.954Z","domain":"prod.rewardsplatform.microsoft.com","root":"microsoft.com","tracker":"microsoft","type":"A","dnssec":false,"encrypted":false,"protocol":"UDP","clientIp":"2804:678c:c176:d500:d47:6f35:ada:bde0","status":"default","reasons":[]},{"timestamp":"2024-11-23T01:19:43.952Z","domain":"prod.rewardsplatform.microsoft.com","root":"microsoft.com","tracker":"microsoft","type":"AAAA","dnssec":false,"encrypted":false,"protocol":"UDP","clientIp":"2804:678c:c176:d500:d47:6f35:ada:bde0","status":"default","reasons":[]},{"timestamp":"2024-11-23T01:19:43.857Z","domain":"self.events.data.microsoft.com","root":"microsoft.com","tracker":"microsoft","type":"A","dnssec":false,"encrypted":false,"protocol":"UDP","clientIp":"2804:678c:c176:d500:d47:6f35:ada:bde0","status":"default","reasons":[]},{"timestamp":"2024-11-23T01:19:43.854Z","domain":"self.events.data.microsoft.com","root":"microsoft.com","tracker":"microsoft","type":"AAAA","dnssec":false,"encrypted":false,"protocol":"UDP","clientIp":"2804:678c:c176:d500:d47:6f35:ada:bde0","status":"default","reasons":[]},{"timestamp":"2024-11-23T01:19:43.580Z","domain":"mobile.events.data.microsoft.com","root":"microsoft.com","tracker":"microsoft","type":"AAAA","dnssec":false,"encrypted":false,"protocol":"UDP","clientIp":"2804:678c:c176:d500:d47:6f35:ada:bde0","status":"default","reasons":[]},{"timestamp":"2024-11-23T01:19:43.580Z","domain":"mobile.events.data.microsoft.com","root":"microsoft.com","tracker":"microsoft","type":"A","dnssec":false,"encrypted":false,"protocol":"UDP","clientIp":"2804:678c:c176:d500:d47:6f35:ada:bde0","status":"default","reasons":[]},{"timestamp":"2024-11-23T01:19:43.393Z","domain":"gateway.bingviz.microsoftapp.net","root":"microsoftapp.net","type":"A","dnssec":false,"encrypted":false,"protocol":"UDP","clientIp":"2804:678c:c176:d500:d47:6f35:ada:bde0","status":"default","reasons":[]},{"timestamp":"2024-11-23T01:19:43.391Z","domain":"gateway.bingviz.microsoftapp.net","root":"microsoftapp.net","type":"AAAA","dnssec":false,"encrypted":false,"protocol":"UDP","clientIp":"2804:678c:c176:d500:d47:6f35:ada:bde0","status":"default","reasons":[]},{"timestamp":"2024-11-23T01:19:43.323Z","domain":"www.bing.com","root":"bing.com","tracker":"bing_ads","type":"AAAA","dnssec":false,"encrypted":false,"protocol":"UDP","clientIp":"2804:678c:c176:d500:d47:6f35:ada:bde0","status":"default","reasons":[]},{"timestamp":"2024-11-23T01:19:43.323Z","domain":"www.bing.com","root":"bing.com","tracker":"bing_ads","type":"A","dnssec":false,"encrypted":false,"protocol":"UDP","clientIp":"2804:678c:c176:d500:d47:6f35:ada:bde0","status":"default","reasons":[]},{"timestamp":"2024-11-23T01:19:42.511Z","domain":"config.edge.skype.com","root":"skype.com","tracker":"skype","type":"AAAA","dnssec":false,"encrypted":false,"protocol":"UDP","clientIp":"2804:678c:c176:d500:d47:6f35:ada:bde0","status":"default","reasons":[]},{"timestamp":"2024-11-23T01:19:42.511Z","domain":"config.edge.skype.com","root":"skype.com","tracker":"skype","type":"A","dnssec":false,"encrypted":false,"protocol":"UDP","clientIp":"2804:678c:c176:d500:d47:6f35:ada:bde0","status":"default","reasons":[]},{"timestamp":"2024-11-23T01:19:28.369Z","domain":"in.appcenter.ms","root":"appcenter.ms","type":"AAAA","dnssec":false,"encrypted":false,"protocol":"UDP","clientIp":"2804:678c:c176:d500:d47:6f35:ada:bde0","status":"default","reasons":[]},{"timestamp":"2024-11-23T01:19:28.369Z","domain":"in.appcenter.ms","root":"appcenter.ms","type":"A","dnssec":false,"encrypted":false,"protocol":"UDP","clientIp":"2804:678c:c176:d500:d47:6f35:ada:bde0","status":"default","reasons":[]},{"timestamp":"2024-11-23T01:19:27.174Z","domain":"yildun.iad-03.braze.com","root":"braze.com","type":"AAAA","dnssec":false,"encrypted":false,"protocol":"UDP","clientIp":"2804:678c:c176:d500:d47:6f35:ada:bde0","status":"default","reasons":[]},{"timestamp":"2024-11-23T01:19:27.172Z","domain":"yildun.iad-03.braze.com","root":"braze.com","type":"A","dnssec":false,"encrypted":false,"protocol":"UDP","clientIp":"2804:678c:c176:d500:d47:6f35:ada:bde0","status":"default","reasons":[]},{"timestamp":"2024-11-23T01:19:26.287Z","domain":"experiment-allocation.yelp.com","root":"yelp.com","type":"A","dnssec":false,"encrypted":false,"protocol":"UDP","clientIp":"2804:678c:c176:d500:d47:6f35:ada:bde0","status":"default","reasons":[]},{"timestamp":"2024-11-23T01:19:26.287Z","domain":"experiment-allocation.yelp.com","root":"yelp.com","type":"AAAA","dnssec":false,"encrypted":false,"protocol":"UDP","clientIp":"2804:678c:c176:d500:d47:6f35:ada:bde0","status":"default","reasons":[]},{"timestamp":"2024-11-23T01:19:26.250Z","domain":"experiment-allocation.yelp.com","root":"yelp.com","type":"A","dnssec":false,"encrypted":false,"protocol":"UDP","clientIp":"2804:678c:c176:d500:d47:6f35:ada:bde0","status":"default","reasons":[]},{"timestamp":"2024-11-23T01:19:26.248Z","domain":"experiment-allocation.yelp.com","root":"yelp.com","type":"AAAA","dnssec":false,"encrypted":false,"protocol":"UDP","clientIp":"2804:678c:c176:d500:d47:6f35:ada:bde0","status":"default","reasons":[]},{"timestamp":"2024-11-23T01:19:26.240Z","domain":"auto-api.yelp.com","root":"yelp.com","type":"A","dnssec":false,"encrypted":false,"protocol":"UDP","clientIp":"2804:678c:c176:d500:d47:6f35:ada:bde0","status":"default","reasons":[]},{"timestamp":"2024-11-23T01:19:26.236Z","domain":"auto-api.yelp.com","root":"yelp.com","type":"AAAA","dnssec":false,"encrypted":false,"protocol":"UDP","clientIp":"2804:678c:c176:d500:d47:6f35:ada:bde0","status":"default","reasons":[]},{"timestamp":"2024-11-23T01:19:25.733Z","domain":"android.apis.google.com","root":"google.com","tracker":"google","type":"A","dnssec":false,"encrypted":false,"protocol":"UDP","clientIp":"2804:678c:c176:d500:d47:6f35:ada:bde0","status":"default","reasons":[]},{"timestamp":"2024-11-23T01:19:25.730Z","domain":"android.apis.google.com","root":"google.com","tracker":"google","type":"AAAA","dnssec":false,"encrypted":false,"protocol":"UDP","clientIp":"2804:678c:c176:d500:d47:6f35:ada:bde0","status":"default","reasons":[]},{"timestamp":"2024-11-23T01:19:25.662Z","domain":"oneclient.sfx.ms","root":"sfx.ms","type":"A","dnssec":false,"encrypted":false,"protocol":"UDP","clientIp":"2804:678c:c176:d500:d47:6f35:ada:bde0","status":"default","reasons":[]},{"timestamp":"2024-11-23T01:19:25.656Z","domain":"oneclient.sfx.ms","root":"sfx.ms","type":"AAAA","dnssec":false,"encrypted":false,"protocol":"UDP","clientIp":"2804:678c:c176:d500:d47:6f35:ada:bde0","status":"default","reasons":[]},{"timestamp":"2024-11-23T01:19:25.564Z","domain":"www.linkedin.com","root":"linkedin.com","tracker":"linkedin","type":"AAAA","dnssec":false,"encrypted":false,"protocol":"UDP","clientIp":"2804:678c:c176:d500:d47:6f35:ada:bde0","status":"default","reasons":[]},{"timestamp":"2024-11-23T01:19:25.564Z","domain":"www.linkedin.com","root":"linkedin.com","tracker":"linkedin","type":"A","dnssec":false,"encrypted":false,"protocol":"UDP","clientIp":"2804:678c:c176:d500:d47:6f35:ada:bde0","status":"default","reasons":[]},{"timestamp":"2024-11-23T01:19:25.470Z","domain":"bunsen.yelp.com","root":"yelp.com","type":"A","dnssec":false,"encrypted":false,"protocol":"UDP","clientIp":"2804:678c:c176:d500:d47:6f35:ada:bde0","status":"default","reasons":[]},{"timestamp":"2024-11-23T01:19:25.418Z","domain":"bunsen.yelp.com","root":"yelp.com","type":"AAAA","dnssec":false,"encrypted":false,"protocol":"UDP","clientIp":"2804:678c:c176:d500:d47:6f35:ada:bde0","status":"default","reasons":[]},{"timestamp":"2024-11-23T01:19:18.049Z","domain":"web.facebook.com","root":"facebook.com","tracker":"facebook","type":"A","dnssec":false,"encrypted":false,"protocol":"UDP","clientIp":"2804:678c:c176:d500:d47:6f35:ada:bde0","status":"default","reasons":[]},{"timestamp":"2024-11-23T01:19:18.047Z","domain":"b-graph.facebook.com","root":"facebook.com","tracker":"facebook","type":"A","dnssec":false,"encrypted":false,"protocol":"UDP","clientIp":"2804:678c:c176:d500:d47:6f35:ada:bde0","status":"default","reasons":[]},{"timestamp":"2024-11-23T01:19:18.047Z","domain":"b-graph.facebook.com","root":"facebook.com","tracker":"facebook","type":"AAAA","dnssec":false,"encrypted":false,"protocol":"UDP","clientIp":"2804:678c:c176:d500:d47:6f35:ada:bde0","status":"default","reasons":[]},{"timestamp":"2024-11-23T01:19:18.046Z","domain":"web.facebook.com","root":"facebook.com","tracker":"facebook","type":"AAAA","dnssec":false,"encrypted":false,"protocol":"UDP","clientIp":"2804:678c:c176:d500:d47:6f35:ada:bde0","status":"default","reasons":[]},{"timestamp":"2024-11-23T01:18:27.731Z","domain":"ta-image.eu","root":"ta-image.eu","type":"A","dnssec":false,"encrypted":false,"protocol":"UDP","clientIp":"2804:678c:c176:d500:d47:6f35:ada:bde0","status":"default","reasons":[]},{"timestamp":"2024-11-23T01:18:27.084Z","domain":"crashlyticsreports-pa.googleapis.com","root":"crashlyticsreports-pa.googleapis.com","tracker":"googleapis.com","type":"AAAA","dnssec":false,"encrypted":false,"protocol":"UDP","clientIp":"2804:678c:c176:d500:d47:6f35:ada:bde0","status":"default","reasons":[]},{"timestamp":"2024-11-23T01:18:27.084Z","domain":"crashlyticsreports-pa.googleapis.com","root":"crashlyticsreports-pa.googleapis.com","tracker":"googleapis.com","type":"A","dnssec":false,"encrypted":false,"protocol":"UDP","clientIp":"2804:678c:c176:d500:d47:6f35:ada:bde0","status":"default","reasons":[]},{"timestamp":"2024-11-23T01:18:25.832Z","domain":"epdg.epc.mnc010.mcc724.pub.3gppnetwork.org","root":"3gppnetwork.org","type":"A","dnssec":false,"encrypted":false,"protocol":"UDP","clientIp":"45.190.211.150","status":"default","reasons":[]},{"timestamp":"2024-11-23T01:18:25.805Z","domain":"epdg.epc.mnc010.mcc724.pub.3gppnetwork.org","root":"3gppnetwork.org","type":"A","dnssec":false,"encrypted":false,"protocol":"UDP","clientIp":"45.190.211.150","status":"default","reasons":[]}],"meta":{"pagination":{"cursor":"64vk6chk68u3ec1n70r3a"},"stream":{"id":"64vk6chk68u3ge9p6gukc"}}}